generateCitationNetwork/__init__.py
generateCitationNetwork/dimGenerateCitationNetwork.py
generateCitationNetwork/generateCitationNetwork.py
generateCitationNetwork-0.3.0a6.dist-info/AUTHORS.rst
generateCitationNetwork-0.3.0a6.dist-info/LICENSE
generateCitationNetwork-0.3.0a6.dist-info/METADATA
generateCitationNetwork-0.3.0a6.dist-info/WHEEL
generateCitationNetwork-0.3.0a6.dist-info/top_level.txt
generateCitationNetwork-0.3.0a6.dist-info/RECORD
