Metadata-Version: 2.1
Name: generateCitationNetwork
Version: 0.3.0a6
Summary: A tool to generate a network of cited and         referenced papers for a given DOI.     
Home-page: https://gitlab.gwdg.de/GMPG/generatecitationnet
Author: Malte Vogl, Robert Egel
Author-email: mvogl@mpiwg-berlin.mpg.de, regel@mpiwg-berlin.mpg.de
License: MIT License
Keywords: generateCitationNetwork
Platform: UNKNOWN
Classifier: Development Status :: 2 - Pre-Alpha
Classifier: Intended Audience :: Science/Research
Classifier: Intended Audience :: Developers
Classifier: License :: OSI Approved :: MIT License
Classifier: Natural Language :: English
Classifier: Programming Language :: Python :: 3.9
License-File: LICENSE
License-File: AUTHORS.rst
Requires-Dist: pandas
Requires-Dist: numpy
Requires-Dist: pysolr
Requires-Dist: nbsphinx
Requires-Dist: dimcli
